odoo/addons/account_voucher_print/README.rst
odoo/addons/account_voucher_print/__init__.py
odoo/addons/account_voucher_print/__manifest__.py
odoo/addons/account_voucher_print/i18n/account_voucher_print.pot
odoo/addons/account_voucher_print/i18n/it.po
odoo/addons/account_voucher_print/models/__init__.py
odoo/addons/account_voucher_print/models/account_voucher.py
odoo/addons/account_voucher_print/readme/CONTRIBUTORS.rst
odoo/addons/account_voucher_print/readme/DESCRIPTION.rst
odoo/addons/account_voucher_print/static/description/icon.png
odoo/addons/account_voucher_print/static/description/index.html
odoo/addons/account_voucher_print/views/account_report.xml
odoo/addons/account_voucher_print/views/report_receipt.xml
odoo12_addon_account_voucher_print-12.0.1.0.0.99.dev7.dist-info/METADATA
odoo12_addon_account_voucher_print-12.0.1.0.0.99.dev7.dist-info/WHEEL
odoo12_addon_account_voucher_print-12.0.1.0.0.99.dev7.dist-info/top_level.txt
odoo12_addon_account_voucher_print-12.0.1.0.0.99.dev7.dist-info/RECORD
